apengs_server_utils/__init__.py
apengs_server_utils/bio.py
apengs_server_utils/chinese_calendar.py
apengs_server_utils/com.py
apengs_server_utils/linkDB.py
apengs_server_utils-0.1.0.dist-info/licenses/LICENSE
apengs_server_utils-0.1.0.dist-info/METADATA
apengs_server_utils-0.1.0.dist-info/WHEEL
apengs_server_utils-0.1.0.dist-info/top_level.txt
apengs_server_utils-0.1.0.dist-info/RECORD
