Metadata-Version: 2.4
Name: apengs-server-utils
Version: 0.1.0
Summary: 高效的数据库操作工具库，封装了MySQL和DuckDB的常用操作，支持数据同步、批量处理和缓存机制
Author-email: apengs <humphrey.abc@gmail.com>
Keywords: mysql,duckdb,database,data-sync,pandas
Classifier: Programming Language :: Python :: 3
Classifier: License :: OSI Approved :: MIT License
Classifier: Operating System :: OS Independent
Classifier: Topic :: Database
Classifier: Topic :: Database :: Front-Ends
Classifier: Topic :: Software Development :: Libraries :: Python Modules
Requires-Python: >=3.9
License-File: LICENSE
Requires-Dist: pandas
Requires-Dist: pymysql
Requires-Dist: duckdb
Requires-Dist: sqlalchemy
Requires-Dist: pdf2image
Requires-Dist: pywinrm
Requires-Dist: PyPDF2
Dynamic: license-file
